tailwind_palette/__init__.py
tailwind_palette/colors.py
tailwind_palette/utils.py
tailwind_palette-1.0.5.dist-info/LICENSE.md
tailwind_palette-1.0.5.dist-info/METADATA
tailwind_palette-1.0.5.dist-info/WHEEL
tailwind_palette-1.0.5.dist-info/top_level.txt
tailwind_palette-1.0.5.dist-info/RECORD
