Metadata-Version: 2.1
Name: tailwind-palette
Version: 1.0.5
Summary: A Python package for working with the Tailwind CSS color palette.
Home-page: https://github.com/noahyoungs/tailwind-palette
Author: Noah Youngs
License: UNKNOWN
Platform: UNKNOWN
